{"y_coordinate": "1909929", "year": "2013", "domestic": false, "case_number": "HW296994", "id": "9151572", "primary_type": "THEFT", "district": "025", "arrest": false, "location": {"type": "Point", "coordinates": [-87.79642221410757, 41.90911556707533]}, "community_area": "25", "latitude": "41.90911556707533", "type": "property", "description": "FROM BUILDING", "beat": "2513", "date": {"$date": 1369861200000}, "ward": "36", "_id": {"$oid": "51b349e93c002ed20d78bcbb"}, "iucr": "890", "longitude": "-87.79642221410757", "location_description": "RESIDENCE PORCH/HALLWAY", "x_coordinate": "1130397", "updated_on": {"$date": 1370306580000}, "fbi_code": "06", "block": "068XX W NORTH AVE"}