{
    "y_coordinate": "1911874", 
    "year": "2013", 
    "domestic": true, 
    "case_number": "HW287994", 
    "id": "9143036", 
    "primary_type": "BATTERY", 
    "district": "025", 
    "arrest": false, 
    "location": {
        "type": "Point", 
        "coordinates": [
            -87.77513490416187, 
            41.914351600288775
        ]
    }, 
    "community_area": "25", 
    "latitude": "41.914351600288775", 
    "type": null, 
    "description": "DOMESTIC BATTERY SIMPLE", 
    "beat": "2531", 
    "date": {
        "$date": 1369330200000
    }, 
    "ward": "29", 
    "_id": {
        "$oid": "51aa13963c002ed20d78b281"
    }, 
    "iucr": "486", 
    "longitude": "-87.77513490416187", 
    "location_description": "APARTMENT", 
    "x_coordinate": "1136179", 
    "updated_on": {
        "$date": 1370133629000
    }, 
    "fbi_code": "08B", 
    "block": "059XX W CORTLAND ST"
}