{"y_coordinate": "1920435", "year": "2013", "domestic": true, "case_number": "HW291908", "id": "9146299", "primary_type": "BATTERY", "district": "025", "arrest": true, "location": {"type": "Point", "coordinates": [-87.72372677727049, 41.93758351364224]}, "community_area": "21", "latitude": "41.93758351364224", "type": "violent", "description": "AGGRAVATED OF A SENIOR CITIZEN", "beat": "2523", "date": {"$date": 1369573200000}, "ward": "30", "_id": {"$oid": "51b34a0a3c002ed20d78c766"}, "iucr": "495", "longitude": "-87.72372677727049", "location_description": "APARTMENT", "x_coordinate": "1150111", "updated_on": {"$date": 1369787985000}, "fbi_code": "04B", "block": "031XX N DAVLIN CT"}