{"y_coordinate": "1937661", "year": "2013", "domestic": false, "case_number": "HW298223", "id": "9153089", "primary_type": "PUBLIC PEACE VIOLATION", "district": "016", "arrest": false, "location": {"type": "Point", "coordinates": [-87.79342569811043, 41.98520423920725]}, "community_area": "10", "latitude": "41.98520423920725", "type": null, "description": "OTHER VIOLATION", "beat": "1612", "date": {"$date": 1369994700000}, "ward": "41", "_id": {"$oid": "51b349ce3c002ed20d78b7fc"}, "iucr": "2890", "longitude": "-87.79342569811043", "location_description": "SCHOOL, PUBLIC, BUILDING", "x_coordinate": "1131038", "updated_on": {"$date": 1370392932000}, "fbi_code": "26", "block": "057XX N NATOMA AVE"}