{
    "y_coordinate": "1913364", 
    "year": "2013", 
    "domestic": false, 
    "case_number": "HW302482", 
    "id": "9157232", 
    "primary_type": "BATTERY", 
    "district": "014", 
    "arrest": true, 
    "location": {
        "type": "Point", 
        "coordinates": [
            -87.69454825662434, 
            41.91802047520882
        ]
    }, 
    "community_area": "22", 
    "latitude": "41.91802047520882", 
    "type": null, 
    "description": "SIMPLE", 
    "beat": "1431", 
    "date": {
        "$date": 1370265300000
    }, 
    "ward": "1", 
    "_id": {
        "$oid": "51b7429d3c002ed20d78d414"
    }, 
    "iucr": "460", 
    "longitude": "-87.69454825662434", 
    "location_description": "SCHOOL, PUBLIC, BUILDING", 
    "x_coordinate": "1158103", 
    "updated_on": {
        "$date": 1370565766000
    }, 
    "fbi_code": "08B", 
    "block": "020XX N POINT ST"
}