{
    "y_coordinate": "1901595", 
    "year": "2013", 
    "domestic": false, 
    "case_number": "HW301827", 
    "id": "9156015", 
    "primary_type": "NARCOTICS", 
    "district": "012", 
    "arrest": true, 
    "location": {
        "type": "Point", 
        "coordinates": [
            -87.66186438570222, 
            41.885537099527
        ]
    }, 
    "community_area": "28", 
    "latitude": "41.885537099527", 
    "type": "quality", 
    "description": "POSS: CANNABIS 30GMS OR LESS", 
    "beat": "1215", 
    "date": {
        "$date": 1370215500000
    }, 
    "ward": "27", 
    "_id": {
        "$oid": "51b5f1153c002ed20d78cbfc"
    }, 
    "iucr": "1811", 
    "longitude": "-87.66186438570222", 
    "location_description": "RESTAURANT", 
    "x_coordinate": "1167091", 
    "updated_on": {
        "$date": 1370392932000
    }, 
    "fbi_code": "18", 
    "block": "013XX W LAKE ST"
}