{"community_area": "42", "_id": {"$oid": "51b34a153c002ed20d78cb40"}, "primary_type": "KIDNAPPING", "beat": "0312", "year": "2013", "domestic": false, "iucr": "1792", "arrest": false, "location_description": "STREET", "location": {"type": "Point", "coordinates": [-87.60576940977236, 41.77982939649972]}, "case_number": "HW308636", "date": {"$date": 1369411200000}, "updated_on": {"$date": 1370651988000}, "ward": "20", "fbi_code": "20", "type": null, "id": "9163929", "block": "063XX S COTTAGE GROVE AVE", "description": "CHILD ABDUCTION/STRANGER"}