{
    "y_coordinate": "1862817", 
    "year": "2013", 
    "domestic": false, 
    "case_number": "HW319303", 
    "id": "9175137", 
    "primary_type": "DECEPTIVE PRACTICE", 
    "district": "003", 
    "arrest": false, 
    "location": {
        "type": "Point", 
        "coordinates": [
            -87.60574829536328, 
            41.778778200134255
        ]
    }, 
    "community_area": "42", 
    "latitude": "41.778778200134255", 
    "type": null, 
    "description": "UNLAWFUL USE OF RECORDED SOUND", 
    "beat": "0312", 
    "date": {
        "$date": 1371254160000
    }, 
    "ward": "20", 
    "_id": {
        "$oid": "51c5c3113c002ed20d79586d"
    }, 
    "iucr": "1235", 
    "longitude": "-87.60574829536328", 
    "location_description": "RESTAURANT", 
    "x_coordinate": "1182701", 
    "updated_on": {
        "$date": 1371516126000
    }, 
    "fbi_code": "11", 
    "block": "063XX S COTTAGE GROVE AVE"
}