{
    "y_coordinate": "1865996", 
    "year": "2013", 
    "domestic": true, 
    "case_number": "HW321662", 
    "id": "9176793", 
    "primary_type": "CRIMINAL DAMAGE", 
    "district": "008", 
    "arrest": true, 
    "location": {
        "type": "Point", 
        "coordinates": [
            -87.73296512800533, 
            41.78823756909905
        ]
    }, 
    "community_area": "62", 
    "latitude": "41.78823756909905", 
    "type": "quality", 
    "description": "TO VEHICLE", 
    "beat": "0813", 
    "date": {
        "$date": 1371408600000
    }, 
    "ward": "13", 
    "_id": {
        "$oid": "51c92aff018e783f00ab5fba"
    }, 
    "iucr": "1320", 
    "longitude": "-87.73296512800533", 
    "location_description": "STREET", 
    "x_coordinate": "1147978", 
    "updated_on": {
        "$date": 1371602404000
    }, 
    "fbi_code": "14", 
    "block": "057XX S KOSTNER AVE"
}