{
    "y_coordinate": "1856522", 
    "year": "2013", 
    "domestic": false, 
    "case_number": "HW321756", 
    "id": "9176850", 
    "primary_type": "NARCOTICS", 
    "district": "007", 
    "arrest": true, 
    "location": {
        "type": "Point", 
        "coordinates": [
            -87.67675673199673, 
            41.76193061493466
        ]
    }, 
    "community_area": "67", 
    "latitude": "41.76193061493466", 
    "type": "quality", 
    "description": "POSS: CANNABIS 30GMS OR LESS", 
    "beat": "0735", 
    "date": {
        "$date": 1371412680000
    }, 
    "ward": "17", 
    "_id": {
        "$oid": "51c92afe018e783f00ab5f8b"
    }, 
    "iucr": "1811", 
    "longitude": "-87.67675673199673", 
    "location_description": "STREET", 
    "x_coordinate": "1163380", 
    "updated_on": {
        "$date": 1371602404000
    }, 
    "fbi_code": "18", 
    "block": "021XX W 72ND PL"
}