{
    "y_coordinate": "1886723", 
    "year": "2013", 
    "domestic": true, 
    "case_number": "HW320428", 
    "id": "9175906", 
    "primary_type": "BATTERY", 
    "district": "009", 
    "arrest": false, 
    "location": {
        "type": "Point", 
        "coordinates": [
            -87.66601983463939, 
            41.84474880153514
        ]
    }, 
    "community_area": "31", 
    "latitude": "41.84474880153514", 
    "type": null, 
    "description": "DOMESTIC BATTERY SIMPLE", 
    "beat": "0912", 
    "date": {
        "$date": 1371323400000
    }, 
    "ward": "11", 
    "_id": {
        "$oid": "51c92b0b018e783f00ab630b"
    }, 
    "iucr": "486", 
    "longitude": "-87.66601983463939", 
    "location_description": "STREET", 
    "x_coordinate": "1166075", 
    "updated_on": {
        "$date": 1371688802000
    }, 
    "fbi_code": "08B", 
    "block": "026XX S ASHLAND AVE"
}