{
    "y_coordinate": "1884185", 
    "year": "2013", 
    "domestic": false, 
    "case_number": "HW339705", 
    "id": "9194868", 
    "primary_type": "OTHER OFFENSE", 
    "district": "010", 
    "arrest": false, 
    "location": {
        "type": "Point", 
        "coordinates": [
            -87.70987999934503, 
            41.838030308143466
        ]
    }, 
    "community_area": "30", 
    "latitude": "41.838030308143466", 
    "type": null, 
    "description": "FALSE/STOLEN/ALTERED TRP", 
    "beat": "1032", 
    "date": {
        "$date": 1372449600000
    }, 
    "ward": "22", 
    "_id": {
        "$oid": "51d83818018e783f00ab8d08"
    }, 
    "iucr": "502P", 
    "longitude": "-87.70987999934503", 
    "location_description": "STREET", 
    "x_coordinate": "1154142", 
    "updated_on": {
        "$date": 1372812143000
    }, 
    "fbi_code": "26", 
    "block": "030XX S HOMAN AVE"
}