{
    "y_coordinate": "1859076", 
    "year": "2013", 
    "domestic": false, 
    "case_number": "HW337036", 
    "id": "9192053", 
    "primary_type": "ROBBERY", 
    "district": "003", 
    "arrest": false, 
    "location": {
        "type": "Point", 
        "coordinates": [
            -87.61277002412082, 
            41.76855605958395
        ]
    }, 
    "community_area": "69", 
    "latitude": "41.76855605958395", 
    "type": "violent", 
    "description": "ATTEMPT: ARMED-HANDGUN", 
    "beat": "0322", 
    "date": {
        "$date": 1372294920000
    }, 
    "ward": "6", 
    "_id": {
        "$oid": "51d59511018e783f00ab8509"
    }, 
    "iucr": "033A", 
    "longitude": "-87.61277002412082", 
    "location_description": "SIDEWALK", 
    "x_coordinate": "1180817", 
    "updated_on": {
        "$date": 1373589638000
    }, 
    "fbi_code": "03", 
    "block": "069XX S EBERHART AVE"
}