{
    "y_coordinate": "1942395", 
    "year": "2013", 
    "domestic": false, 
    "case_number": "HW341541", 
    "id": "9196268", 
    "primary_type": "THEFT", 
    "district": "024", 
    "arrest": false, 
    "location": {
        "type": "Point", 
        "coordinates": [
            -87.6880870776194, 
            41.997651502653454
        ]
    }, 
    "community_area": "2", 
    "latitude": "41.997651502653454", 
    "type": "property", 
    "description": "OVER $500", 
    "beat": "2413", 
    "date": {
        "$date": 1372550460000
    }, 
    "ward": "50", 
    "_id": {
        "$oid": "51dadb19018e783f00ab9319"
    }, 
    "iucr": "810", 
    "longitude": "-87.6880870776194", 
    "location_description": "VEHICLE NON-COMMERCIAL", 
    "x_coordinate": "1159643", 
    "updated_on": {
        "$date": 1372812143000
    }, 
    "fbi_code": "06", 
    "block": "023XX W DEVON AVE"
}