{
    "y_coordinate": "1908051", 
    "year": "2013", 
    "domestic": false, 
    "case_number": "HW348493", 
    "id": "9203107", 
    "primary_type": "BATTERY", 
    "district": "018", 
    "arrest": false, 
    "location": {
        "type": "Point", 
        "coordinates": [
            -87.62918590547578, 
            41.90305816416978
        ]
    }, 
    "community_area": "8", 
    "latitude": "41.90305816416978", 
    "type": null, 
    "description": "SIMPLE", 
    "beat": "1824", 
    "date": {
        "$date": 1372982460000
    }, 
    "ward": "42", 
    "_id": {
        "$oid": "51e0211b018e783f00aba0fc"
    }, 
    "iucr": "460", 
    "longitude": "-87.62918590547578", 
    "location_description": "PARKING LOT/GARAGE(NON.RESID.)", 
    "x_coordinate": "1175937", 
    "updated_on": {
        "$date": 1373157603000
    }, 
    "fbi_code": "08B", 
    "block": "0000X W ELM ST"
}