{
    "y_coordinate": "1940599", 
    "year": "2013", 
    "domestic": false, 
    "case_number": "HW340465", 
    "id": "9195478", 
    "primary_type": "BURGLARY", 
    "district": "024", 
    "arrest": false, 
    "location": {
        "type": "Point", 
        "coordinates": [
            -87.66049416306656, 
            41.992564519466406
        ]
    }, 
    "community_area": "77", 
    "latitude": "41.992564519466406", 
    "type": "property", 
    "description": "UNLAWFUL ENTRY", 
    "beat": "2433", 
    "date": {
        "$date": 1372480200000
    }, 
    "ward": "48", 
    "_id": {
        "$oid": "51d83812018e783f00ab8b98"
    }, 
    "iucr": "620", 
    "longitude": "-87.66049416306656", 
    "location_description": "GROCERY FOOD STORE", 
    "x_coordinate": "1167158", 
    "updated_on": {
        "$date": 1373416728000
    }, 
    "fbi_code": "05", 
    "block": "060XX N BROADWAY"
}