{
    "y_coordinate": "1852999", 
    "year": "2013", 
    "domestic": true, 
    "case_number": "HW344649", 
    "id": "9199327", 
    "primary_type": "OFFENSE INVOLVING CHILDREN", 
    "district": "006", 
    "arrest": false, 
    "location": {
        "type": "Point", 
        "coordinates": [
            -87.64422598356452, 
            41.75207192786556
        ]
    }, 
    "community_area": "71", 
    "latitude": "41.75207192786556", 
    "type": null, 
    "description": "OTHER OFFENSE", 
    "beat": "0621", 
    "date": {
        "$date": 1372761300000
    }, 
    "ward": "17", 
    "_id": {
        "$oid": "51dd7e24018e783f00ab9bfe"
    }, 
    "iucr": "1780", 
    "longitude": "-87.64422598356452", 
    "location_description": "POLICE FACILITY/VEH PARKING LOT", 
    "x_coordinate": "1172284", 
    "updated_on": {
        "$date": 1373848785000
    }, 
    "fbi_code": "26", 
    "block": "078XX S HALSTED ST"
}