{
    "y_coordinate": "1860745", 
    "year": "2013", 
    "domestic": true, 
    "case_number": "HW348815", 
    "id": "9203482", 
    "primary_type": "BATTERY", 
    "district": "007", 
    "arrest": true, 
    "location": {
        "type": "Point", 
        "coordinates": [
            -87.64840841704977, 
            41.773354281355374
        ]
    }, 
    "community_area": "68", 
    "latitude": "41.773354281355374", 
    "type": null, 
    "description": "DOMESTIC BATTERY SIMPLE", 
    "beat": "0723", 
    "date": {
        "$date": 1373004000000
    }, 
    "ward": "17", 
    "_id": {
        "$oid": "51e1729c018e783f00aba742"
    }, 
    "iucr": "486", 
    "longitude": "-87.64840841704977", 
    "location_description": "RESIDENCE", 
    "x_coordinate": "1171081", 
    "updated_on": {
        "$date": 1373244025000
    }, 
    "fbi_code": "08B", 
    "block": "066XX S SANGAMON ST"
}