{
    "y_coordinate": "1942680", 
    "year": "2013", 
    "domestic": false, 
    "case_number": "HW355099", 
    "id": "9208981", 
    "primary_type": "MOTOR VEHICLE THEFT", 
    "district": "024", 
    "arrest": false, 
    "location": {
        "type": "Point", 
        "coordinates": [
            -87.68395538002584, 
            41.99841029820569
        ]
    }, 
    "community_area": "2", 
    "latitude": "41.99841029820569", 
    "type": "property", 
    "description": "CYCLE, SCOOTER, BIKE W-VIN", 
    "beat": "2412", 
    "date": {
        "$date": 1373371200000
    }, 
    "ward": "50", 
    "_id": {
        "$oid": "51fde779733824919a2967c7"
    }, 
    "iucr": "917", 
    "longitude": "-87.68395538002584", 
    "location_description": "RESIDENCE-GARAGE", 
    "x_coordinate": "1160764", 
    "updated_on": {
        "$date": 1375317661000
    }, 
    "fbi_code": "07", 
    "block": "064XX N HAMILTON AVE"
}