{
    "y_coordinate": "1924122", 
    "year": "2013", 
    "domestic": false, 
    "case_number": "HW356949", 
    "id": "9210795", 
    "primary_type": "OTHER OFFENSE", 
    "district": "019", 
    "arrest": true, 
    "location": {
        "type": "Point", 
        "coordinates": [
            -87.656301650152, 
            41.94732365064203
        ]
    }, 
    "community_area": "6", 
    "latitude": "41.94732365064203", 
    "type": null, 
    "description": "OTHER CRIME AGAINST PERSON", 
    "beat": "1923", 
    "date": {
        "$date": 1373489100000
    }, 
    "ward": "44", 
    "_id": {
        "$oid": "51fde776733824919a2962e0"
    }, 
    "iucr": "5000", 
    "longitude": "-87.656301650152", 
    "location_description": "SIDEWALK", 
    "x_coordinate": "1168428", 
    "updated_on": {
        "$date": 1373675960000
    }, 
    "fbi_code": "26", 
    "block": "010XX W ADDISON ST"
}