{
    "y_coordinate": "1910146", 
    "year": "2013", 
    "domestic": false, 
    "case_number": "HW354034", 
    "id": "9207847", 
    "primary_type": "THEFT", 
    "district": "025", 
    "arrest": false, 
    "location": {
        "type": "Point", 
        "coordinates": [
            -87.74886573690625, 
            41.90947885762135
        ]
    }, 
    "community_area": "25", 
    "latitude": "41.90947885762135", 
    "type": "property", 
    "description": "FROM BUILDING", 
    "beat": "2533", 
    "date": {
        "$date": 1373315400000
    }, 
    "ward": "37", 
    "_id": {
        "$oid": "51fde77a733824919a296990"
    }, 
    "iucr": "890", 
    "longitude": "-87.74886573690625", 
    "location_description": "ATHLETIC CLUB", 
    "x_coordinate": "1143341", 
    "updated_on": {
        "$date": 1373675960000
    }, 
    "fbi_code": "06", 
    "block": "049XX W NORTH AVE"
}