{
    "y_coordinate": "1869799", 
    "year": "2013", 
    "domestic": false, 
    "case_number": "HW359038", 
    "id": "9212956", 
    "primary_type": "BATTERY", 
    "district": "009", 
    "arrest": false, 
    "location": {
        "type": "Point", 
        "coordinates": [
            -87.69012234881444, 
            41.79844220967464
        ]
    }, 
    "community_area": "63", 
    "latitude": "41.79844220967464", 
    "type": null, 
    "description": "SIMPLE", 
    "beat": "0923", 
    "date": {
        "$date": 1373538600000
    }, 
    "ward": "14", 
    "_id": {
        "$oid": "51fde775733824919a296166"
    }, 
    "iucr": "460", 
    "longitude": "-87.69012234881444", 
    "location_description": "SCHOOL, PUBLIC, BUILDING", 
    "x_coordinate": "1159634", 
    "updated_on": {
        "$date": 1373848785000
    }, 
    "fbi_code": "08B", 
    "block": "052XX S TALMAN AVE"
}