{
    "y_coordinate": "1894303", 
    "year": "2013", 
    "domestic": false, 
    "case_number": "HW355014", 
    "id": "9208811", 
    "primary_type": "NARCOTICS", 
    "district": "010", 
    "arrest": true, 
    "location": {
        "type": "Point", 
        "coordinates": [
            -87.69602734424204, 
            41.865720707550466
        ]
    }, 
    "community_area": "29", 
    "latitude": "41.865720707550466", 
    "type": "quality", 
    "description": "MANU/DELIVER:CRACK", 
    "beat": "1022", 
    "date": {
        "$date": 1373382900000
    }, 
    "ward": "24", 
    "_id": {
        "$oid": "51fde779733824919a296730"
    }, 
    "iucr": "2017", 
    "longitude": "-87.69602734424204", 
    "location_description": "PARK PROPERTY", 
    "x_coordinate": "1157842", 
    "updated_on": {
        "$date": 1373589638000
    }, 
    "fbi_code": "18", 
    "block": "012XX S CALIFORNIA BLVD"
}