{
    "y_coordinate": "1870151", 
    "year": "2013", 
    "domestic": false, 
    "case_number": "HW350819", 
    "id": "9205043", 
    "primary_type": "THEFT", 
    "district": "008", 
    "arrest": false, 
    "location": {
        "type": "Point", 
        "coordinates": [
            -87.71490722955721, 
            41.799544299873624
        ]
    }, 
    "community_area": "62", 
    "latitude": "41.799544299873624", 
    "type": "property", 
    "description": "FROM BUILDING", 
    "beat": "0822", 
    "date": {
        "$date": 1373115600000
    }, 
    "ward": "23", 
    "_id": {
        "$oid": "51e415a5018e783f00abad20"
    }, 
    "iucr": "890", 
    "longitude": "-87.71490722955721", 
    "location_description": "RESIDENCE-GARAGE", 
    "x_coordinate": "1152873", 
    "updated_on": {
        "$date": 1373675960000
    }, 
    "fbi_code": "06", 
    "block": "051XX S MILLARD AVE"
}