{
    "y_coordinate": "1844283", 
    "year": "2013", 
    "domestic": false, 
    "case_number": "HW364240", 
    "id": "9217489", 
    "primary_type": "ROBBERY", 
    "district": "022", 
    "arrest": false, 
    "location": {
        "type": "Point", 
        "coordinates": [
            -87.66706893861887, 
            41.72828724346988
        ]
    }, 
    "community_area": "72", 
    "latitude": "41.72828724346988", 
    "type": "violent", 
    "description": "ARMED: HANDGUN", 
    "beat": "2221", 
    "date": {
        "$date": 1373914800000
    }, 
    "ward": "19", 
    "_id": {
        "$oid": "51fde769733824919a29516d"
    }, 
    "iucr": "031A", 
    "longitude": "-87.66706893861887", 
    "location_description": "SIDEWALK", 
    "x_coordinate": "1166118", 
    "updated_on": {
        "$date": 1375749778000
    }, 
    "fbi_code": "03", 
    "block": "091XX S BEVERLY AVE"
}