{
    "y_coordinate": "1828606", 
    "year": "2013", 
    "domestic": false, 
    "case_number": "HW360743", 
    "id": "9214595", 
    "primary_type": "THEFT", 
    "district": "005", 
    "arrest": false, 
    "location": {
        "type": "Point", 
        "coordinates": [
            -87.63439779496319, 
            41.68507037478197
        ]
    }, 
    "community_area": "53", 
    "latitude": "41.68507037478197", 
    "type": "property", 
    "description": "$500 AND UNDER", 
    "beat": "0522", 
    "date": {
        "$date": 1373729400000
    }, 
    "ward": "34", 
    "_id": {
        "$oid": "51fde76f733824919a29595d"
    }, 
    "iucr": "820", 
    "longitude": "-87.63439779496319", 
    "location_description": "SMALL RETAIL STORE", 
    "x_coordinate": "1175164", 
    "updated_on": {
        "$date": 1373935219000
    }, 
    "fbi_code": "06", 
    "block": "004XX W 115TH ST"
}