{
    "y_coordinate": "1864845", 
    "year": "2013", 
    "domestic": false, 
    "case_number": "HW362901", 
    "id": "9215992", 
    "primary_type": "BATTERY", 
    "district": "008", 
    "arrest": false, 
    "location": {
        "type": "Point", 
        "coordinates": [
            -87.6912591830517, 
            41.784853363512305
        ]
    }, 
    "community_area": "66", 
    "latitude": "41.784853363512305", 
    "type": null, 
    "description": "DOMESTIC BATTERY SIMPLE", 
    "beat": "0824", 
    "date": {
        "$date": 1373853600000
    }, 
    "ward": "16", 
    "_id": {
        "$oid": "51fde76b733824919a2953db"
    }, 
    "iucr": "486", 
    "longitude": "-87.6912591830517", 
    "location_description": "ALLEY", 
    "x_coordinate": "1159361", 
    "updated_on": {
        "$date": 1374194525000
    }, 
    "fbi_code": "08B", 
    "block": "059XX S WASHTENAW AVE"
}