{
    "y_coordinate": "1926684", 
    "year": "2013", 
    "domestic": false, 
    "case_number": "HW378340", 
    "id": "9232143", 
    "primary_type": "THEFT", 
    "district": "019", 
    "arrest": false, 
    "location": {
        "type": "Point", 
        "coordinates": [
            -87.64533492487847, 
            41.954289124700566
        ]
    }, 
    "community_area": "6", 
    "latitude": "41.954289124700566", 
    "type": "property", 
    "description": "FROM BUILDING", 
    "beat": "1925", 
    "date": {
        "$date": 1374555600000
    }, 
    "ward": "46", 
    "_id": {
        "$oid": "51fde747733824919a293782"
    }, 
    "iucr": "890", 
    "longitude": "-87.64533492487847", 
    "location_description": "RESIDENCE", 
    "x_coordinate": "1171391", 
    "updated_on": {
        "$date": 1375836149000
    }, 
    "fbi_code": "06", 
    "block": "039XX N LAKE SHORE DR"
}