{
    "y_coordinate": "1901414", 
    "year": "2013", 
    "domestic": false, 
    "case_number": "HW376603", 
    "id": "9230512", 
    "primary_type": "NARCOTICS", 
    "district": "015", 
    "arrest": true, 
    "location": {
        "type": "Point", 
        "coordinates": [
            -87.7655872499056, 
            41.88560002428738
        ]
    }, 
    "community_area": "25", 
    "latitude": "41.88560002428738", 
    "type": "quality", 
    "description": "POSS: CANNABIS 30GMS OR LESS", 
    "beat": "1512", 
    "date": {
        "$date": 1374654120000
    }, 
    "ward": "29", 
    "_id": {
        "$oid": "51fde740733824919a2933ee"
    }, 
    "iucr": "1811", 
    "longitude": "-87.7655872499056", 
    "location_description": "STREET", 
    "x_coordinate": "1138847", 
    "updated_on": {
        "$date": 1374971969000
    }, 
    "fbi_code": "18", 
    "block": "056XX W FULTON ST"
}