{
    "y_coordinate": "1872332", 
    "year": "2013", 
    "domestic": true, 
    "case_number": "HW372622", 
    "id": "9225807", 
    "primary_type": "OTHER OFFENSE", 
    "district": "008", 
    "arrest": true, 
    "location": {
        "type": "Point", 
        "coordinates": [
            -87.73958067334024, 
            41.805659766305745
        ]
    }, 
    "community_area": "56", 
    "latitude": "41.805659766305745", 
    "type": null, 
    "description": "OTHER VEHICLE OFFENSE", 
    "beat": "0815", 
    "date": {
        "$date": 1373846460000
    }, 
    "ward": "23", 
    "_id": {
        "$oid": "51fde76b733824919a295423"
    }, 
    "iucr": "5002", 
    "longitude": "-87.73958067334024", 
    "location_description": "STREET", 
    "x_coordinate": "1146130", 
    "updated_on": {
        "$date": 1375231290000
    }, 
    "fbi_code": "26", 
    "block": "048XX S KNOX AVE"
}