{
    "y_coordinate": "1853909", 
    "year": "2013", 
    "domestic": false, 
    "case_number": "HW372987", 
    "id": "9225987", 
    "primary_type": "CRIMINAL DAMAGE", 
    "district": "006", 
    "arrest": false, 
    "location": {
        "type": "Point", 
        "coordinates": [
            -87.64306688410494, 
            41.75456228645454
        ]
    }, 
    "community_area": "71", 
    "latitude": "41.75456228645454", 
    "type": "quality", 
    "description": "TO PROPERTY", 
    "beat": "0621", 
    "date": {
        "$date": 1374435060000
    }, 
    "ward": "17", 
    "_id": {
        "$oid": "51fde751733824919a293c7a"
    }, 
    "iucr": "1310", 
    "longitude": "-87.64306688410494", 
    "location_description": "APARTMENT", 
    "x_coordinate": "1172593", 
    "updated_on": {
        "$date": 1374971969000
    }, 
    "fbi_code": "14", 
    "block": "076XX S EMERALD AVE"
}