{
    "y_coordinate": "1897673", 
    "year": "2013", 
    "domestic": false, 
    "case_number": "HW382511", 
    "id": "9235718", 
    "primary_type": "OTHER OFFENSE", 
    "district": "011", 
    "arrest": false, 
    "location": {
        "type": "Point", 
        "coordinates": [
            -87.72708176792669, 
            41.875136969333504
        ]
    }, 
    "community_area": "26", 
    "latitude": "41.875136969333504", 
    "type": null, 
    "description": "SEX OFFENDER: FAIL REG NEW ADD", 
    "beat": "1132", 
    "date": {
        "$date": 1375001100000
    }, 
    "ward": "24", 
    "_id": {
        "$oid": "520116d0733824919a297254"
    }, 
    "iucr": "4651", 
    "longitude": "-87.72708176792669", 
    "location_description": "APARTMENT", 
    "x_coordinate": "1149359", 
    "updated_on": {
        "$date": 1375922568000
    }, 
    "fbi_code": "26", 
    "block": "040XX W VAN BUREN ST"
}