{
    "y_coordinate": "1926800", 
    "year": "2013", 
    "domestic": false, 
    "case_number": "HW383818", 
    "id": "9236938", 
    "primary_type": "THEFT", 
    "district": "016", 
    "arrest": false, 
    "location": {
        "type": "Point", 
        "coordinates": [
            -87.75779336732705, 
            41.95522628585156
        ]
    }, 
    "community_area": "15", 
    "latitude": "41.95522628585156", 
    "type": "property", 
    "description": "$500 AND UNDER", 
    "beat": "1624", 
    "date": {
        "$date": 1374480000000
    }, 
    "ward": "38", 
    "_id": {
        "$oid": "51fde74f733824919a293ad7"
    }, 
    "iucr": "820", 
    "longitude": "-87.75779336732705", 
    "location_description": "RESIDENCE-GARAGE", 
    "x_coordinate": "1140799", 
    "updated_on": {
        "$date": 1376009150000
    }, 
    "fbi_code": "06", 
    "block": "052XX W BELLE PLAINE AVE"
}