{
    "y_coordinate": "1884710", 
    "year": "2013", 
    "domestic": false, 
    "case_number": "HW387248", 
    "id": "9241473", 
    "primary_type": "THEFT", 
    "district": "009", 
    "arrest": false, 
    "location": {
        "type": "Point", 
        "coordinates": [
            -87.66564055341483, 
            41.83922239538347
        ]
    }, 
    "community_area": "31", 
    "latitude": "41.83922239538347", 
    "type": "property", 
    "description": "OVER $500", 
    "beat": "0913", 
    "date": {
        "$date": 1375284000000
    }, 
    "ward": "11", 
    "_id": {
        "$oid": "5203b9d8733824919a297b76"
    }, 
    "iucr": "810", 
    "longitude": "-87.66564055341483", 
    "location_description": "CTA TRAIN", 
    "x_coordinate": "1166194", 
    "updated_on": {
        "$date": 1375836149000
    }, 
    "fbi_code": "06", 
    "block": "030XX S ASHLAND AVE"
}