{
    "y_coordinate": "1861470", 
    "year": "2013", 
    "domestic": true, 
    "case_number": "HW386714", 
    "id": "9240785", 
    "primary_type": "OTHER OFFENSE", 
    "district": "003", 
    "arrest": false, 
    "location": {
        "type": "Point", 
        "coordinates": [
            -87.60516321747168, 
            41.77507793460188
        ]
    }, 
    "community_area": "42", 
    "latitude": "41.77507793460188", 
    "type": null, 
    "description": "TELEPHONE THREAT", 
    "beat": "0321", 
    "date": {
        "$date": 1375254000000
    }, 
    "ward": "20", 
    "_id": {
        "$oid": "5203b9dd733824919a297ca8"
    }, 
    "iucr": "2820", 
    "longitude": "-87.60516321747168", 
    "location_description": "RESIDENCE", 
    "x_coordinate": "1182872", 
    "updated_on": {
        "$date": 1375490414000
    }, 
    "fbi_code": "26", 
    "block": "008XX E MARQUETTE RD"
}