{
    "y_coordinate": "1934687", 
    "year": "2013", 
    "domestic": false, 
    "case_number": "HW399106", 
    "id": "9254199", 
    "primary_type": "CRIMINAL DAMAGE", 
    "district": "017", 
    "arrest": false, 
    "location": {
        "type": "Point", 
        "coordinates": [
            -87.72841412107472, 
            41.97671881927723
        ]
    }, 
    "community_area": "13", 
    "latitude": "41.97671881927723", 
    "type": "quality", 
    "description": "TO VEHICLE", 
    "beat": "1712", 
    "date": {
        "$date": 1375983000000
    }, 
    "ward": "39", 
    "_id": {
        "$oid": "5214dd61733824919a29a7ac"
    }, 
    "iucr": "1320", 
    "longitude": "-87.72841412107472", 
    "location_description": "PARKING LOT/GARAGE(NON.RESID.)", 
    "x_coordinate": "1148735", 
    "updated_on": {
        "$date": 1376181721000
    }, 
    "fbi_code": "14", 
    "block": "052XX N PULASKI RD"
}