{
    "y_coordinate": "1870756", 
    "year": "2013", 
    "domestic": true, 
    "case_number": "HW391703", 
    "id": "9246137", 
    "primary_type": "CRIMINAL DAMAGE", 
    "district": "009", 
    "arrest": false, 
    "location": {
        "type": "Point", 
        "coordinates": [
            -87.65762166987558, 
            41.80088191295361
        ]
    }, 
    "community_area": "61", 
    "latitude": "41.80088191295361", 
    "type": "quality", 
    "description": "TO PROPERTY", 
    "beat": "0934", 
    "date": {
        "$date": 1375541400000
    }, 
    "ward": "16", 
    "_id": {
        "$oid": "520ba2eb733824919a299097"
    }, 
    "iucr": "1310", 
    "longitude": "-87.65762166987558", 
    "location_description": "APARTMENT", 
    "x_coordinate": "1168489", 
    "updated_on": {
        "$date": 1376354397000
    }, 
    "fbi_code": "14", 
    "block": "051XX S THROOP ST"
}