{
    "y_coordinate": "1858444", 
    "year": "2013", 
    "domestic": true, 
    "case_number": "HW391934", 
    "id": "9246236", 
    "primary_type": "THEFT", 
    "district": "007", 
    "arrest": false, 
    "location": {
        "type": "Point", 
        "coordinates": [
            -87.6361232034811, 
            41.7669657593203
        ]
    }, 
    "community_area": "68", 
    "latitude": "41.7669657593203", 
    "type": "property", 
    "description": "FROM BUILDING", 
    "beat": "0732", 
    "date": {
        "$date": 1375473600000
    }, 
    "ward": "6", 
    "_id": {
        "$oid": "52065cd0733824919a2981f8"
    }, 
    "iucr": "890", 
    "longitude": "-87.6361232034811", 
    "location_description": "APARTMENT", 
    "x_coordinate": "1174451", 
    "updated_on": {
        "$date": 1375749778000
    }, 
    "fbi_code": "06", 
    "block": "070XX S EGGLESTON AVE"
}