{
    "y_coordinate": "1912711", 
    "year": "2013", 
    "domestic": false, 
    "case_number": "HW391099", 
    "id": "9245645", 
    "primary_type": "BURGLARY", 
    "district": "014", 
    "arrest": false, 
    "location": {
        "type": "Point", 
        "coordinates": [
            -87.68752315271384, 
            41.91618919712519
        ]
    }, 
    "community_area": "22", 
    "latitude": "41.91618919712519", 
    "type": "property", 
    "description": "FORCIBLE ENTRY", 
    "beat": "1434", 
    "date": {
        "$date": 1375509600000
    }, 
    "ward": "1", 
    "_id": {
        "$oid": "520ba2ef733824919a2991be"
    }, 
    "iucr": "610", 
    "longitude": "-87.68752315271384", 
    "location_description": "RESTAURANT", 
    "x_coordinate": "1160020", 
    "updated_on": {
        "$date": 1376527473000
    }, 
    "fbi_code": "05", 
    "block": "019XX N WESTERN AVE"
}