{
    "y_coordinate": "1858603", 
    "year": "2013", 
    "domestic": false, 
    "case_number": "HW396503", 
    "id": "9250979", 
    "primary_type": "GAMBLING", 
    "district": "007", 
    "arrest": true, 
    "location": {
        "type": "Point", 
        "coordinates": [
            -87.6564615809134, 
            41.76752372719851
        ]
    }, 
    "community_area": "67", 
    "latitude": "41.76752372719851", 
    "type": null, 
    "description": "GAME/DICE", 
    "beat": "0734", 
    "date": {
        "$date": 1375822800000
    }, 
    "ward": "17", 
    "_id": {
        "$oid": "520ba2ae733824919a29860c"
    }, 
    "iucr": "1661", 
    "longitude": "-87.6564615809134", 
    "location_description": "SIDEWALK", 
    "x_coordinate": "1168901", 
    "updated_on": {
        "$date": 1376181721000
    }, 
    "fbi_code": "19", 
    "block": "069XX S THROOP ST"
}