{
    "y_coordinate": "1859504", 
    "year": "2013", 
    "domestic": false, 
    "case_number": "HW401909", 
    "id": "9256804", 
    "primary_type": "BURGLARY", 
    "district": "007", 
    "arrest": false, 
    "location": {
        "type": "Point", 
        "coordinates": [
            -87.66138412043418, 
            41.77002523518267
        ]
    }, 
    "community_area": "67", 
    "latitude": "41.77002523518267", 
    "type": "property", 
    "description": "ATTEMPT FORCIBLE ENTRY", 
    "beat": "0725", 
    "date": {
        "$date": 1376134200000
    }, 
    "ward": "17", 
    "_id": {
        "$oid": "5214dd55733824919a29a275"
    }, 
    "iucr": "630", 
    "longitude": "-87.66138412043418", 
    "location_description": "RESIDENCE-GARAGE", 
    "x_coordinate": "1167551", 
    "updated_on": {
        "$date": 1376527473000
    }, 
    "fbi_code": "05", 
    "block": "068XX S LAFLIN ST"
}