{
    "y_coordinate": "1834237", 
    "year": "2013", 
    "domestic": false, 
    "case_number": "HW404293", 
    "id": "9259254", 
    "primary_type": "OTHER OFFENSE", 
    "district": "022", 
    "arrest": false, 
    "location": {
        "type": "Point", 
        "coordinates": [
            -87.63433667832356, 
            41.70052333475655
        ]
    }, 
    "community_area": "49", 
    "latitude": "41.70052333475655", 
    "type": null, 
    "description": "SEX OFFENDER: FAIL REG NEW ADD", 
    "beat": "2233", 
    "date": {
        "$date": 1376305200000
    }, 
    "ward": "34", 
    "_id": {
        "$oid": "5214dd45733824919a299bab"
    }, 
    "iucr": "4651", 
    "longitude": "-87.63433667832356", 
    "location_description": "RESIDENCE", 
    "x_coordinate": "1175135", 
    "updated_on": {
        "$date": 1376613678000
    }, 
    "fbi_code": "26", 
    "block": "106XX S EGGLESTON AVE"
}