{
    "y_coordinate": "1921153", 
    "year": "2013", 
    "domestic": false, 
    "case_number": "HW404286", 
    "id": "9260698", 
    "primary_type": "CRIMINAL DAMAGE", 
    "district": "017", 
    "arrest": false, 
    "location": {
        "type": "Point", 
        "coordinates": [
            -87.70575412511948, 
            41.939457033145
        ]
    }, 
    "community_area": "21", 
    "latitude": "41.939457033145", 
    "type": "quality", 
    "description": "TO PROPERTY", 
    "beat": "1733", 
    "date": {
        "$date": 1376387400000
    }, 
    "ward": "33", 
    "_id": {
        "$oid": "5214dd37733824919a299852"
    }, 
    "iucr": "1310", 
    "longitude": "-87.70575412511948", 
    "location_description": "SMALL RETAIL STORE", 
    "x_coordinate": "1154996", 
    "updated_on": {
        "$date": 1376613678000
    }, 
    "fbi_code": "14", 
    "block": "031XX W BELMONT AVE"
}