{
    "y_coordinate": "1942388", 
    "year": "2013", 
    "domestic": false, 
    "case_number": "HW408590", 
    "id": "9263985", 
    "primary_type": "OTHER OFFENSE", 
    "district": "024", 
    "arrest": false, 
    "location": {
        "type": "Point", 
        "coordinates": [
            -87.67029376831947, 
            41.9975308975602
        ]
    }, 
    "community_area": "77", 
    "latitude": "41.9975308975602", 
    "type": null, 
    "description": "TELEPHONE THREAT", 
    "beat": "2433", 
    "date": {
        "$date": 1376557800000
    }, 
    "ward": "40", 
    "_id": {
        "$oid": "52178040733824919a29af1a"
    }, 
    "iucr": "2820", 
    "longitude": "-87.67029376831947", 
    "location_description": "APARTMENT", 
    "x_coordinate": "1164480", 
    "updated_on": {
        "$date": 1376786529000
    }, 
    "fbi_code": "26", 
    "block": "063XX N CLARK ST"
}