{
    "y_coordinate": "1850273", 
    "year": "2013", 
    "domestic": true, 
    "case_number": "HW401844", 
    "id": "9256737", 
    "primary_type": "BATTERY", 
    "district": "004", 
    "arrest": false, 
    "location": {
        "type": "Point", 
        "coordinates": [
            -87.55775695837785, 
            41.744039809925674
        ]
    }, 
    "community_area": "46", 
    "latitude": "41.744039809925674", 
    "type": null, 
    "description": "DOMESTIC BATTERY SIMPLE", 
    "beat": "0423", 
    "date": {
        "$date": 1376145300000
    }, 
    "ward": "7", 
    "_id": {
        "$oid": "5214dd54733824919a29a1fe"
    }, 
    "iucr": "486", 
    "longitude": "-87.55775695837785", 
    "location_description": "RESIDENCE", 
    "x_coordinate": "1195905", 
    "updated_on": {
        "$date": 1376354397000
    }, 
    "fbi_code": "08B", 
    "block": "083XX S MANISTEE AVE"
}