{
    "y_coordinate": "1906170", 
    "year": "2013", 
    "domestic": true, 
    "case_number": "HW402560", 
    "id": "9257250", 
    "primary_type": "OTHER OFFENSE", 
    "district": "015", 
    "arrest": false, 
    "location": {
        "type": "Point", 
        "coordinates": [
            -87.74819023657285, 
            41.8985643245848
        ]
    }, 
    "community_area": "25", 
    "latitude": "41.8985643245848", 
    "type": null, 
    "description": "OTHER VEHICLE OFFENSE", 
    "beat": "1531", 
    "date": {
        "$date": 1376146800000
    }, 
    "ward": "37", 
    "_id": {
        "$oid": "5214dd54733824919a29a1e9"
    }, 
    "iucr": "5002", 
    "longitude": "-87.74819023657285", 
    "location_description": "STREET", 
    "x_coordinate": "1143552", 
    "updated_on": {
        "$date": 1376527473000
    }, 
    "fbi_code": "26", 
    "block": "009XX N LAMON AVE"
}