{
    "y_coordinate": "1849545", 
    "year": "2013", 
    "domestic": false, 
    "case_number": "HW408720", 
    "id": "9264088", 
    "primary_type": "CRIMINAL DAMAGE", 
    "district": "006", 
    "arrest": false, 
    "location": {
        "type": "Point", 
        "coordinates": [
            -87.60484056883323, 
            41.74235012909273
        ]
    }, 
    "community_area": "44", 
    "latitude": "41.74235012909273", 
    "type": "quality", 
    "description": "TO PROPERTY", 
    "beat": "0632", 
    "date": {
        "$date": 1376517600000
    }, 
    "ward": "8", 
    "_id": {
        "$oid": "52178043733824919a29b017"
    }, 
    "iucr": "1310", 
    "longitude": "-87.60484056883323", 
    "location_description": "RESTAURANT", 
    "x_coordinate": "1183061", 
    "updated_on": {
        "$date": 1376786529000
    }, 
    "fbi_code": "14", 
    "block": "083XX S COTTAGE GROVE AVE"
}