{
    "y_coordinate": "1904009", 
    "year": "2013", 
    "domestic": false, 
    "case_number": "HW407270", 
    "id": "9262712", 
    "primary_type": "THEFT", 
    "district": "012", 
    "arrest": false, 
    "location": {
        "type": "Point", 
        "coordinates": [
            -87.68269926319843, 
            41.89228163340837
        ]
    }, 
    "community_area": "24", 
    "latitude": "41.89228163340837", 
    "type": "property", 
    "description": "$500 AND UNDER", 
    "beat": "1221", 
    "date": {
        "$date": 1376469000000
    }, 
    "ward": "26", 
    "_id": {
        "$oid": "52178049733824919a29b259"
    }, 
    "iucr": "820", 
    "longitude": "-87.68269926319843", 
    "location_description": "STREET", 
    "x_coordinate": "1161399", 
    "updated_on": {
        "$date": 1376700033000
    }, 
    "fbi_code": "06", 
    "block": "022XX W OHIO ST"
}