{
    "y_coordinate": "1850828", 
    "year": "2013", 
    "domestic": false, 
    "case_number": "HW402491", 
    "id": "9257214", 
    "primary_type": "ROBBERY", 
    "district": "008", 
    "arrest": false, 
    "location": {
        "type": "Point", 
        "coordinates": [
            -87.68346763142121, 
            41.74634269226412
        ]
    }, 
    "community_area": "70", 
    "latitude": "41.74634269226412", 
    "type": "violent", 
    "description": "ATTEMPT: STRONGARM-NO WEAPON", 
    "beat": "0835", 
    "date": {
        "$date": 1376178000000
    }, 
    "ward": "18", 
    "_id": {
        "$oid": "5214dd50733824919a29a034"
    }, 
    "iucr": "340", 
    "longitude": "-87.68346763142121", 
    "location_description": "STREET", 
    "x_coordinate": "1161592", 
    "updated_on": {
        "$date": 1376700033000
    }, 
    "fbi_code": "03", 
    "block": "024XX W 81ST ST"
}