{
    "y_coordinate": "1856991", 
    "year": "2013", 
    "domestic": false, 
    "case_number": "HW401618", 
    "id": "9256640", 
    "primary_type": "OTHER OFFENSE", 
    "district": "007", 
    "arrest": false, 
    "location": {
        "type": "Point", 
        "coordinates": [
            -87.6560719176, 
            41.76309762103319
        ]
    }, 
    "community_area": "67", 
    "latitude": "41.76309762103319", 
    "type": null, 
    "description": "SEX OFFENDER: FAIL REG NEW ADD", 
    "beat": "0734", 
    "date": {
        "$date": 1376134920000
    }, 
    "ward": "17", 
    "_id": {
        "$oid": "5214dd55733824919a29a271"
    }, 
    "iucr": "4651", 
    "longitude": "-87.6560719176", 
    "location_description": "RESIDENCE", 
    "x_coordinate": "1169020", 
    "updated_on": {
        "$date": 1376440911000
    }, 
    "fbi_code": "26", 
    "block": "012XX W 72ND ST"
}