{
    "y_coordinate": "1897781", 
    "year": "2013", 
    "domestic": true, 
    "case_number": "HW400758", 
    "id": "9255926", 
    "primary_type": "BATTERY", 
    "district": "015", 
    "arrest": false, 
    "location": {
        "type": "Point", 
        "coordinates": [
            -87.7587764091976, 
            41.875596289218436
        ]
    }, 
    "community_area": "25", 
    "latitude": "41.875596289218436", 
    "type": null, 
    "description": "DOMESTIC BATTERY SIMPLE", 
    "beat": "1522", 
    "date": {
        "$date": 1376076300000
    }, 
    "ward": "29", 
    "_id": {
        "$oid": "5214dd5a733824919a29a4a1"
    }, 
    "iucr": "486", 
    "longitude": "-87.7587764091976", 
    "location_description": "RESIDENCE", 
    "x_coordinate": "1140726", 
    "updated_on": {
        "$date": 1376527473000
    }, 
    "fbi_code": "08B", 
    "block": "053XX W GLADYS AVE"
}