{
    "y_coordinate": "1921586", 
    "year": "2013", 
    "domestic": false, 
    "case_number": "HW414626", 
    "id": "9269654", 
    "primary_type": "THEFT", 
    "district": "019", 
    "arrest": false, 
    "location": {
        "type": "Point", 
        "coordinates": [
            -87.6539752881293, 
            41.940350581219874
        ]
    }, 
    "community_area": "6", 
    "latitude": "41.940350581219874", 
    "type": "property", 
    "description": "$500 AND UNDER", 
    "beat": "1924", 
    "date": {
        "$date": 1376798400000
    }, 
    "ward": "44", 
    "_id": {
        "$oid": "521b74b3733824919a29ba31"
    }, 
    "iucr": "820", 
    "longitude": "-87.6539752881293", 
    "location_description": "SIDEWALK", 
    "x_coordinate": "1169081", 
    "updated_on": {
        "$date": 1377304792000
    }, 
    "fbi_code": "06", 
    "block": "032XX N SHEFFIELD AVE"
}