{
    "y_coordinate": "1891522", 
    "year": "2013", 
    "domestic": false, 
    "case_number": "HW412965", 
    "id": "9267855", 
    "primary_type": "NARCOTICS", 
    "district": "010", 
    "arrest": true, 
    "location": {
        "type": "Point", 
        "coordinates": [
            -87.71780395626477, 
            41.85820770692354
        ]
    }, 
    "community_area": "29", 
    "latitude": "41.85820770692354", 
    "type": "quality", 
    "description": "POSS: CANNABIS 30GMS OR LESS", 
    "beat": "1014", 
    "date": {
        "$date": 1376829000000
    }, 
    "ward": "24", 
    "_id": {
        "$oid": "521b74b0733824919a29b972"
    }, 
    "iucr": "1811", 
    "longitude": "-87.71780395626477", 
    "location_description": "ALLEY", 
    "x_coordinate": "1151930", 
    "updated_on": {
        "$date": 1377045742000
    }, 
    "fbi_code": "18", 
    "block": "016XX S LAWNDALE AVE"
}