{
    "y_coordinate": "1871165", 
    "year": "2013", 
    "domestic": true, 
    "case_number": "HW415100", 
    "id": "9270046", 
    "primary_type": "THEFT", 
    "district": "009", 
    "arrest": false, 
    "location": {
        "type": "Point", 
        "coordinates": [
            -87.66251319584998, 
            41.80203299310254
        ]
    }, 
    "community_area": "61", 
    "latitude": "41.80203299310254", 
    "type": "property", 
    "description": "$500 AND UNDER", 
    "beat": "0933", 
    "date": {
        "$date": 1376854200000
    }, 
    "ward": "16", 
    "_id": {
        "$oid": "521b74ab733824919a29b84d"
    }, 
    "iucr": "820", 
    "longitude": "-87.66251319584998", 
    "location_description": "RESIDENCE", 
    "x_coordinate": "1167152", 
    "updated_on": {
        "$date": 1377218448000
    }, 
    "fbi_code": "06", 
    "block": "050XX S LAFLIN ST"
}