{
    "y_coordinate": "1927329", 
    "year": "2013", 
    "domestic": false, 
    "case_number": "HW410451", 
    "id": "9265958", 
    "primary_type": "DECEPTIVE PRACTICE", 
    "district": "019", 
    "arrest": false, 
    "location": {
        "type": "Point", 
        "coordinates": [
            -87.65632615455017, 
            41.956124479019074
        ]
    }, 
    "community_area": "3", 
    "latitude": "41.956124479019074", 
    "type": null, 
    "description": "FRAUD OR CONFIDENCE GAME", 
    "beat": "1915", 
    "date": {
        "$date": 1376492400000
    }, 
    "ward": "46", 
    "_id": {
        "$oid": "52178046733824919a29b151"
    }, 
    "iucr": "1130", 
    "longitude": "-87.65632615455017", 
    "location_description": "APARTMENT", 
    "x_coordinate": "1168396", 
    "updated_on": {
        "$date": 1377045742000
    }, 
    "fbi_code": "11", 
    "block": "040XX N KENMORE AVE"
}